{"iteration":4,"prev_iteration":3,"diffs":[{"filename":"train.py","status":"modified","added_lines":13,"removed_lines":5,"diff":"--- a/train.py\n+++ b/train.py\n@@ -33,6 +33,7 @@\n \n\n     train_transform = transforms.Compose([\n\n         transforms.ToPILImage(),\n\n+        transforms.AutoAugment(transforms.AutoAugmentPolicy.CIFAR10),\n\n         transforms.RandomResizedCrop(224),\n\n         transforms.RandomHorizontalFlip(),\n\n         transforms.ToTensor(),\n\n@@ -59,9 +60,13 @@\n \n\n     criterion = nn.CrossEntropyLoss(label_smoothing=0.1)\n\n     optimizer = optim.AdamW(model.parameters(), lr=5e-5, weight_decay=1e-4)\n\n-    scheduler = optim.lr_scheduler.CosineAnnealingLR(optimizer, T_max=15)\n\n \n\n-    num_epochs = 15\n\n+    num_epochs = 30\n\n+    scheduler = optim.lr_scheduler.CosineAnnealingLR(optimizer, T_max=num_epochs)\n\n+\n\n+    os.makedirs('checkpoints', exist_ok=True)\n\n+    best_val_acc = 0.0\n\n+    best_path = 'checkpoints/best.pt'\n\n     global_step = 0\n\n \n\n     for epoch in range(num_epochs):\n\n@@ -104,8 +109,11 @@\n         avg_val_loss = val_loss / len(val_loader)\n\n         with open(log_path, 'a') as f:\n\n             f.write(json.dumps({'step': global_step, 'val_loss': avg_val_loss, 'val_acc': val_acc, 'epoch': epoch+1}) + '\\n')\n\n+\n\n+        if val_acc > best_val_acc:\n\n+            best_val_acc = val_acc\n\n+            torch.save(model.state_dict(), best_path)\n\n+            print(f'New best val acc: {val_acc:.4f} at epoch {epoch+1}')\n\n         print(f'Epoch {epoch+1}/{num_epochs} - Val Acc: {val_acc:.4f}')\n\n \n\n-    os.makedirs('checkpoints', exist_ok=True)\n\n-    torch.save(model.state_dict(), 'checkpoints/best.pt')\n\n-    print('Training completed. Model saved to checkpoints/best.pt')\n+    print(f'Training completed. Best model saved to {best_path} with val acc: {best_val_acc:.4f}')"}]}