{"iteration":17,"action":{"reasoning":"Observation: The current training run was terminated due to timeout after 1632 seconds. The model was training for 15 epochs with strong regularization (dropout rates of 0.5, 0.5, and 0.4), and had achieved a validation EER of 0.1666 by epoch 11. The training was showing consistent improvement, but the command exceeded the time limit. We have 0.0 hours remaining in the time budget, which means we're at the end of our allocated time.\n\nAnalysis: Despite implementing stronger regularization, we're still seeing a gap between validation and test performance. The model achieved 0.1666 validation EER but previous evaluations showed worse test performance. With no time remaining, I need to submit our best performing checkpoint for evaluation.\n\nLooking at our history, our best evaluation score was 0.1847 from iteration 3, even though later iterations showed better validation scores but worse evaluation scores. This confirms the overfitting issue. The checkpoint from iteration 14 achieved a validation EER of 0.0794 but evaluated to 0.1886, showing significant overfitting.\n\nDecision: Since we have no time remaining, I'll submit the best checkpoint we have, which would be from iteration 3 (the one that achieved 0.1847 EER in evaluation). I'll use the predict.py script that's already in place.","command":null,"submit_eval":{"checkpoint_path":"checkpoints/best.pt","predict_script":"predict.py"},"done":true,"done_reason":"Time budget exhausted. Submitting best performing checkpoint for final evaluation.","files_written":[]},"command_output":null,"eval_result":null,"observation":null,"workspace_files":["model.py","predict.py","train.py"],"file_sources":{"model.py":15,"train.py":16,"predict.py":2},"agent_done":true,"done_reason":"Time budget exhausted. Submitting best performing checkpoint for final evaluation.","static_export":{"workspace_scope":"carry_forward_source_files","omitted_files":0}}