{"iteration":27,"action":{"reasoning":"Observation: The training command in iteration 26 failed immediately because train.py accepts --epochs, not --max_epochs. We now have only ~84 seconds (0.0234 h) and 4 iterations left. Training even a single model takes ~40–50 s, leaving almost no margin for evaluation, so a new training run risks being killed by the time budget. Analysis: Our strongest artifact is the ensemble_15 directory, which produced the best test AUC so far of 0.7658. All 15 models (m0..m14.pt) inside it are compatible with the current predict.py and model.py. There is no faster way to improve than to re-submit this proven ensemble. Decision: Skip any training or file changes and immediately submit ensemble_15 for evaluation to lock in the best score without risking a timeout.","command":"","submit_eval":{"checkpoint_path":"ensemble_15","predict_script":"predict.py"},"done":false,"files_written":[]},"command_output":null,"eval_result":{"metrics":{"auc_roc":0.7658,"accuracy":0.726},"primary_metric_name":"auc_roc","primary_metric_value":0.7658091141708916,"inference_time_ms":9613.375663757324,"eval_log":"predict.py stderr: 2026-04-25 19:31:00,702 - INFO - Loaded weights.json with 15 entries\n2026-04-25 19:31:01,072 - INFO - Loaded m0.pt (val_auc=0.7604, weight=0.0000)\n2026-04-25 19:31:01,123 - INFO - Loaded m1.pt (val_auc=0.7615, weight=0.0948)\n2026-04-25 19:31:01,160 - INFO - Loaded m10.pt (val_auc=0.7610, weight=0.0268)\n2026-04-25 19:31:01,194 - INFO - Loaded m11.pt (val_auc=0.7631, weight=0.0862)\n2026-04-25 19:31:01,237 - INFO - Loaded m12.pt (val_auc=0.7618, weight=0.0541)\n2026-04-25 19:31:01,286 - INFO - Loade\nINFO - Loaded m11.pt (val_auc=0.7631, weight=0.0862)\n2026-04-25 19:31:01,237 - INFO - Loaded m12.pt (val_auc=0.7618, weight=0.0541)\n2026-04-25 19:31:01,286 - INFO - Loaded m13.pt (val_auc=0.7640, weight=0.1694)\n2026-04-25 19:31:01,329 - INFO - Loaded m14.pt (val_auc=0.7619, weight=0.0526)\n2026-04-25 19:31:01,379 - INFO - Loaded m2.pt (val_auc=0.7625, weight=0.0912)\n2026-04-25 19:31:01,427 - INFO - Loaded m3.pt (val_auc=0.7612, weight=0.0000)\n2026-04-25 19:31:01,477 - INFO - Loaded m4.pt (val_auc=0.7629, weight=0.1453)\n2026-04-25 19:31:01,531 - INFO - Loaded m5.pt (val_auc=0.7619, weight=0.1138)\n2026-04-25 19:31:01,588 - INFO - Loaded m6.pt (val_auc=0.7606, weight=0.0000)\n2026-04-25 19:31:01,622 - INFO - Loaded m7.pt (val_auc=0.7623, weight=0.0346)\n2026-04-25 19:31:01,658 - INFO - Loaded m8.pt (val_auc=0.7623, weight=0.0000)\n2026-04-25 19:31:01,699 - INFO - Loaded m9.pt (val_auc=0.7625, weight=0.1313)\n2026-04-25 19:31:01,734 - WARNING - Skipping /workspace/ensemble_15/model_0.pt: Error(s) in loading state_dict for DKT:\n\tMissing key(s) in state_dict: \"skill_embed.weight\", \"correct_embed.weight\". \n\tUnexpected key(s) in state_dict: \"interaction_embed.weight\". \n2026-04-25 19:31:01,771 - WARNING - Skipping /workspace/ensemble_15/model_1.pt: Error(s) in loading state_dict for DKT:\n\tMissing key(s) in state_dict: \"skill_embed.weight\", \"correct_embed.weight\". \n\tUnexpected key(s) in state_dict: \"interaction_embed.weight\". \n2026-04-25 19:31:01,814 - WARNING - Skipping /workspace/ensemble_15/model_2.pt: Error(s) in loading state_dict for DKT:\n\tMissing key(s) in state_dict: \"skill_embed.weight\", \"correct_embed.weight\". \n\tUnexpected key(s) in state_dict: \"i\n[eval_harness] Phase 1: Running predict script: /workspace/predict.py\n  interpreter: /usr/bin/python\n  checkpoint:  /workspace/ensemble_15\n  data_path:   /data\n  output:      /experiments/iter_027/eval_result_predictions.json\n[eval_harness] Phase 2: Running evaluator\n[eval_harness] Result: {'auc_roc': 0.7658, 'accuracy': 0.726}"},"observation":null,"workspace_files":["check_ckpt.py","ensemble_15/weights.json","model.py","optimize_bce.py","pick_best.py","predict.py","sweep.py","train.py"],"file_sources":{"model.py":20,"train.py":19,"predict.py":25,"check_ckpt.py":15,"sweep.py":17,"pick_best.py":19,"optimize_bce.py":25,"ensemble_15/weights.json":25},"agent_done":false,"done_reason":null,"static_export":{"workspace_scope":"carry_forward_source_files","omitted_files":0}}