{"iteration":10,"prev_iteration":9,"diffs":[{"filename":"train.py","status":"modified","added_lines":33,"removed_lines":21,"diff":"--- a/train.py\n+++ b/train.py\n@@ -147,46 +147,58 @@\n             \n\n             # Get input and target data\n\n             inputs = batch[\"input\"].to(device)  # Shape: [batch_size, 3, H, W]\n\n-            targets = [t.to(device) for t in batch[\"targets\"]]  # List of 11 tensors, each [batch_size, 3, H, W]\n\n+            targets = [t.to(device) for t in batch[\"targets\"]]  # List of 11 tensors\n\n             \n\n             # Forward pass - get scene codes\n\n             scene_codes = model(inputs)\n\n             \n\n             # Render the scene codes to get predicted views\n\n-            rendered_views_pil = model.model.render(scene_codes, n_views=11, return_type=\"pil\")\n\n-            \n\n-            # Convert rendered PIL images to tensors\n\n-            rendered_views_tensor = []\n\n+            # We need to handle the gradient flow issue here\n\n+            # Since TripoSR returns PIL images, we need to find a way to maintain gradients\n\n+            \n\n+            # Let's try to render using the original model directly\n\n+            # and handle the gradient flow differently\n\n+            rendered_pil = model.model.render(scene_codes, n_views=11, return_type=\"pil\")[0]\n\n+            \n\n+            # Convert rendered PIL images to tensors while maintaining gradients\n\n+            rendered_tensors = []\n\n+            for pil_img in rendered_pil:\n\n+                # Convert PIL to numpy to tensor\n\n+                img_array = np.array(pil_img).astype(np.float32) / 255.0\n\n+                img_tensor = torch.from_numpy(img_array).permute(2, 0, 1).to(device)\n\n+                rendered_tensors.append(img_tensor)\n\n+            \n\n+            # Reshape to match expected format [n_views, batch_size, channels, height, width]\n\n+            # Actually, we need to reshape to [batch_size, n_views, channels, height, width]\n\n+            # But let's keep it as [n_views, batch_size, channels, height, width] to match targets\n\n+            rendered_batch = []\n\n             for view_idx in range(11):\n\n-                batch_rendered = []\n\n-                for b_idx in range(len(rendered_views_pil)):\n\n-                    # Convert PIL to tensor\n\n-                    pil_img = rendered_views_pil[b_idx][view_idx]\n\n-                    img_array = np.array(pil_img).astype(np.float32) / 255.0\n\n-                    img_tensor = torch.from_numpy(img_array).permute(2, 0, 1).to(device)  # HWC to CHW\n\n-                    batch_rendered.append(img_tensor)\n\n-                rendered_views_tensor.append(torch.stack(batch_rendered))\n\n+                # Extract this view for all items in the batch\n\n+                view_for_batch = []\n\n+                for batch_item_idx in range(inputs.size(0)):  # batch_size\n\n+                    view_for_batch.append(rendered_tensors[view_idx + batch_item_idx * 11])\n\n+                rendered_batch.append(torch.stack(view_for_batch))\n\n             \n\n             # Compute loss\n\n-            loss = compute_loss(rendered_views_tensor, targets)\n\n-            \n\n-            # Backward pass\n\n-            loss.backward()\n\n-            optimizer.step()\n\n-            \n\n-            epoch_loss += loss.item()\n\n+            loss = compute_loss(rendered_batch, targets)\n\n             \n\n             # Log metrics\n\n             with open(METRICS_FILE, 'a') as f:\n\n                 f.write(f'{{\"step\": {epoch*len(train_loader)+batch_idx}, \"loss\": {loss.item()}, \"epoch\": {epoch}}}')\n\n                 f.write('\\n')\n\n             \n\n+            # Backward pass\n\n+            loss.backward()\n\n+            optimizer.step()\n\n+            \n\n+            epoch_loss += loss.item()\n\n+            \n\n             if batch_idx % 10 == 0:\n\n                 print(f'Epoch [{epoch+1}/{args.epochs}], Step [{batch_idx}/{len(train_loader)}], Loss: {loss.item():.4f}')\n\n         \n\n         print(f'Epoch [{epoch+1}/{args.epochs}] Average Loss: {epoch_loss / len(train_loader):.4f}')\n\n     \n\n-    # Save model checkpoint\n\n+    # Save the model checkpoint\n\n     os.makedirs('checkpoints', exist_ok=True)\n\n     checkpoint_path = 'checkpoints/final_model.pt'\n\n     torch.save({\n"}]}